LICENSE.txt
MANIFEST.in
README.rst
setup.cfg
setup.py
pmb/__init__.py
pmb/cmd.py
pmb.egg-info/PKG-INFO
pmb.egg-info/SOURCES.txt
pmb.egg-info/dependency_links.txt
pmb.egg-info/top_level.txt